sopel_modules.weather-1.6.1-py3.9-nspkg.pth
sopel_modules/weather/__init__.py
sopel_modules/weather/weather.py
sopel_modules/weather/providers/__init__.py
sopel_modules/weather/providers/weather/__init__.py
sopel_modules/weather/providers/weather/openmeteo.py
sopel_modules/weather/providers/weather/openweathermap.py
sopel_modules/weather/providers/weather/pirateweather.py
sopel_modules.weather-1.6.1.dist-info/LICENSE
sopel_modules.weather-1.6.1.dist-info/METADATA
sopel_modules.weather-1.6.1.dist-info/WHEEL
sopel_modules.weather-1.6.1.dist-info/namespace_packages.txt
sopel_modules.weather-1.6.1.dist-info/top_level.txt
sopel_modules.weather-1.6.1.dist-info/RECORD
