Metadata-Version: 2.1
Name: sopel-modules.weather
Version: 1.6.1
Summary: A working re-implementation of the weather module for Sopel
Home-page: http://github.com/rustybower/sopel-weather
Author: Rusty Bower
Author-email: rusty@rustybower.com
License: MIT License
Platform: UNKNOWN
License-File: LICENSE
Requires-Dist: requests
Requires-Dist: sopel >=7.1
Requires-Dist: pytz
